{
    "output": {
        "order": 1,
        "title": "Output",
        "description": "Learn how to output a value"
    },
    "templateLiterals": {
        "order": 2,
        "title": "Template literals",
        "description": "Learn how to interpolate strings with different data types"
    },
    "variables": {
        "order": 3,
        "title": "Variables",
        "description": "Learn how to store values in a variable"
    },
    "booleans": {
        "order": 4,
        "title": "Booleans",
        "description": "Learn how to evaluate any expression"
    },
    "arithmeticOperators": {
        "order": 5,
        "title": "Arithmetic Operators",
        "description": "Learn how to perform arithmetic operations on variables and values"
    },
    "assignmentOperators": {
        "order": 6,
        "title": "Assignment Operators",
        "description": "Learn how to assign values to variables"
    },
    "comparisonLogicalOperators": {
        "order": 7,
        "title": "Comparison and Logical Operators",
        "description": "Learn how to compare values"
    },
    "conditionalStatements": {
        "order": 8,
        "title": "Conditional Statements",
        "description": "Learn how to make decisions"
    },
    "whileLoops": {
        "order": 9,
        "title": "While Loops",
        "description": "Learn how to repeat a set of statements"
    },
    "forLoops": {
        "order": 10,
        "title": "For Loops",
        "description": "Learn how to repeat a set of statements"
    },
    "arrays": {
        "order": 11,
        "title": "Arrays",
        "description": "Learn how to store different values into one variable"
    },
    "objects": {
        "order": 12,
        "title": "Objects",
        "description": "Learn how to store values with keys"
    },
    "functions": {
        "order": 13,
        "title": "Functions",
        "description": "Learn how to divide code by specific tasks"
    },
    "classes": {
        "order": 14,
        "title": "Classes",
        "description": "Learn object-oriented programming"
    }
}
